{"siteName":"Kimly Parc","logoUrl":"https://kimlyparc.com/cdn/shop/files/logo.png","themeColor":"#f5f5f5","hero":{"title":"Korean café drinks. Made better.","subtitle":"Experience Korean café culture — anywhere, anytime.","ctaText":"Get yours","imageUrl":"https://kimlyparc.com/cdn/shop/files/hero-image.jpg"},"features":[{"title":"Emotional Support Tumbler","description":"Your emotional support tumbler."},{"title":"Original Korean Latte","description":"A reinvention of the beloved Korean instant coffee."},{"title":"Craft Instant Espresso","description":"High-quality instant espresso for a quick fix."}],"secondarySection":{"title":"Why people love KimlyParc","description":"Quality shouldn’t be a luxury and convenience doesn’t have to mean compromise.","imageUrl":"https://kimlyparc.com/cdn/shop/files/featured-section.jpg"},"contact":{"email":"support@kimlyparc.com","address":"123 Kimly Parc Ave, Seoul, South Korea"},"footer":"© 2023 Kimly Parc. All rights reserved.","copyright":"All product images and descriptions are property of Kimly Parc."}